odoo/addons/fieldservice_distribution/README.rst
odoo/addons/fieldservice_distribution/__init__.py
odoo/addons/fieldservice_distribution/__manifest__.py
odoo/addons/fieldservice_distribution/models/__init__.py
odoo/addons/fieldservice_distribution/models/fsm_location.py
odoo/addons/fieldservice_distribution/readme/CONTRIBUTORS.rst
odoo/addons/fieldservice_distribution/readme/CREDITS.rst
odoo/addons/fieldservice_distribution/readme/DESCRIPTION.rst
odoo/addons/fieldservice_distribution/readme/ROADMAP.rst
odoo/addons/fieldservice_distribution/readme/USAGE.rst
odoo/addons/fieldservice_distribution/static/description/icon.png
odoo/addons/fieldservice_distribution/static/description/index.html
odoo/addons/fieldservice_distribution/views/fsm_location.xml
odoo11_addon_fieldservice_distribution-11.0.0.2.0.dist-info/METADATA
odoo11_addon_fieldservice_distribution-11.0.0.2.0.dist-info/RECORD
odoo11_addon_fieldservice_distribution-11.0.0.2.0.dist-info/WHEEL
odoo11_addon_fieldservice_distribution-11.0.0.2.0.dist-info/top_level.txt
